geopython/__init__.py
geopython-1.0.0.dist-info/LICENSE.md
geopython-1.0.0.dist-info/METADATA
geopython-1.0.0.dist-info/WHEEL
geopython-1.0.0.dist-info/top_level.txt
geopython-1.0.0.dist-info/RECORD
